{
    "id": 1691979504064,
    "scene_width": 64000,
    "scene_height": 64000,
    "nodes": [
        {
            "id": 1692021530224,
            "title": "Input",
            "pos_x": -392.0,
            "pos_y": -255.0,
            "inputs": [],
            "outputs": [
                {
                    "id": 1692021675376,
                    "index": 0,
                    "multi_edges": true,
                    "position": 5,
                    "socket_type": 0
                }
            ],
            "content": {
                "id": 1692021530224,
                "content": "content",
                "value": "5"
            },
            "op_code": 1
        },
        {
            "id": 1692021724720,
            "title": "Input",
            "pos_x": -383.0,
            "pos_y": -19.0,
            "inputs": [],
            "outputs": [
                {
                    "id": 1692021780304,
                    "index": 0,
                    "multi_edges": true,
                    "position": 5,
                    "socket_type": 0
                }
            ],
            "content": {
                "id": 1692021724720,
                "content": "content",
                "value": "0"
            },
            "op_code": 1
        },
        {
            "id": 1692021780256,
            "title": "Output",
            "pos_x": 196.0,
            "pos_y": -196.0,
            "inputs": [
                {
                    "id": 1692021916624,
                    "index": 0,
                    "multi_edges": false,
                    "position": 2,
                    "socket_type": 0
                }
            ],
            "outputs": [],
            "content": {
                "id": 1692021780256,
                "content": "content"
            },
            "op_code": 2
        },
        {
            "id": 1692021964960,
            "title": "Add",
            "pos_x": -115.0,
            "pos_y": -149.0,
            "inputs": [
                {
                    "id": 1692022036976,
                    "index": 0,
                    "multi_edges": false,
                    "position": 2,
                    "socket_type": 2
                },
                {
                    "id": 1692022084928,
                    "index": 1,
                    "multi_edges": false,
                    "position": 2,
                    "socket_type": 2
                }
            ],
            "outputs": [
                {
                    "id": 1692022116496,
                    "index": 0,
                    "multi_edges": true,
                    "position": 5,
                    "socket_type": 1
                }
            ],
            "content": {
                "id": 1692021964960,
                "content": "content"
            },
            "op_code": 3
        }
    ],
    "edges": [
        {
            "id": 1692022036928,
            "type": 2,
            "start": 1692021675376,
            "end": 1692022036976
        },
        {
            "id": 1692022194240,
            "type": 2,
            "start": 1692021780304,
            "end": 1692022084928
        },
        {
            "id": 1692022296096,
            "type": 2,
            "start": 1692022116496,
            "end": 1692021916624
        }
    ]
}